Pyttoresque-1.1.1.data/data/etc/jupyter/jupyter_notebook_config.d/pyttoresque.json
Pyttoresque-1.1.1.data/data/etc/jupyter/jupyter_server_config.d/pyttoresque.json
pyttoresque/__init__.py
pyttoresque/analysis.py
pyttoresque/netlist.py
pyttoresque/simserver.py
pyttoresque/api/.gitrepo
pyttoresque/api/LICENSE
pyttoresque/api/README.md
pyttoresque/api/Simulator.capnp
pyttoresque/api/__init__.py
pyttoresque/api/main.cpp
pyttoresque/api/examples/CMakeLists.txt
pyttoresque/api/examples/blink.sp
pyttoresque/api/examples/blink.sp.license
pyttoresque/api/examples/blink.v
pyttoresque/api/examples/blink_multisim.py
pyttoresque/api/examples/main.cpp
pyttoresque/api/examples/rc.sp
pyttoresque/api/examples/rc.sp.license
pyttoresque/app/__init__.py
pyttoresque/app/main.py
pyttoresque/app/theme.yaml
pyttoresque/app/static/bokeh.css
pyttoresque/app/static/common.js
pyttoresque/app/static/common.js.license
pyttoresque/app/static/editor.js
pyttoresque/app/static/editor.js.license
pyttoresque/app/static/libman.js
pyttoresque/app/static/libman.js.license
pyttoresque/app/static/manifest.edn
pyttoresque/app/static/style.css
pyttoresque/app/static/icons/Logo.svg
pyttoresque/app/static/icons/arrows-move.svg
pyttoresque/app/static/icons/eraser.svg
pyttoresque/app/static/icons/pencil.svg
pyttoresque/app/static/icons/search.svg
pyttoresque/app/templates/editor.html
pyttoresque/app/templates/index.html
pyttoresque/app/templates/libman.html
pyttoresque/app/templates/local.ini
Pyttoresque-1.1.1.dist-info/LICENSE
Pyttoresque-1.1.1.dist-info/METADATA
Pyttoresque-1.1.1.dist-info/WHEEL
Pyttoresque-1.1.1.dist-info/entry_points.txt
Pyttoresque-1.1.1.dist-info/top_level.txt
Pyttoresque-1.1.1.dist-info/RECORD
