Metadata-Version: 2.1
Name: Pyttoresque
Version: 1.1.1
Summary: Library for working with NyanCAD tools
Home-page: https://github.com/NyanCAD/pyttoresque
Author: Pepijn de Vos
Author-email: pepijndevos@gmail.com
Classifier: Programming Language :: Python :: 3
Classifier: License :: OSI Approved :: MIT License
Classifier: Operating System :: OS Independent
Requires-Python: >=3.6
License-File: LICENSE
Requires-Dist: aiohttp
Requires-Dist: pycapnp
Requires-Dist: panel
Requires-Dist: holoviews
Requires-Dist: datashader
Requires-Dist: plotly
Requires-Dist: numpy
Requires-Dist: jupyterlab
Requires-Dist: jupyter-server-proxy
